smartextract/__init__.py
smartextract/__main__.py
smartextract/_oauth.py
smartextract-0.6.1.dist-info/METADATA
smartextract-0.6.1.dist-info/WHEEL
smartextract-0.6.1.dist-info/entry_points.txt
smartextract-0.6.1.dist-info/licenses/LICENSE
smartextract-0.6.1.dist-info/RECORD
