Metadata-Version: 2.4
Name: smartextract
Version: 0.6.1
Summary: smartextract Python SDK
Project-URL: Documentation, https://docs.smartextract.ai
Project-URL: Issues, https://github.com/dida-do/smartextract-sdk-python/issues
Project-URL: Source, https://github.com/dida-do/smartextract-sdk-python
Author-email: dida Datenschmiede GmbH <info@dida.do>
License-Expression: MIT
License-File: LICENSE
Classifier: Development Status :: 4 - Beta
Classifier: Programming Language :: Python
Classifier: Programming Language :: Python :: 3.9
Classifier: Programming Language :: Python :: 3.10
Classifier: Programming Language :: Python :: 3.11
Classifier: Programming Language :: Python :: 3.12
Classifier: Programming Language :: Python :: 3.13
Classifier: Programming Language :: Python :: Implementation :: CPython
Classifier: Programming Language :: Python :: Implementation :: PyPy
Requires-Python: >=3.9
Requires-Dist: httpx>=0.25
Requires-Dist: pydantic[email]<3,>=2.0
Provides-Extra: all
Requires-Dist: httpx-oauth>=0.16; extra == 'all'
Requires-Dist: platformdirs>=4.0; extra == 'all'
Requires-Dist: pycomplete>=0.4; extra == 'all'
Requires-Dist: pygments>=2.0; extra == 'all'
Requires-Dist: pyyaml>=5.1; extra == 'all'
Provides-Extra: cli-extras
Requires-Dist: pycomplete>=0.4; extra == 'cli-extras'
Requires-Dist: pygments>=2.0; extra == 'cli-extras'
Requires-Dist: pyyaml>=5.1; extra == 'cli-extras'
Provides-Extra: oauth
Requires-Dist: httpx-oauth>=0.16; extra == 'oauth'
Requires-Dist: platformdirs>=4.0; extra == 'oauth'
